{
  "data": {
    "country": [
      {
        "iso": "AF",
        "name": "Afghanistan",
        "__typename": "country"
      },
      {
        "iso": "AX",
        "name": "Aland Islands",
        "__typename": "country"
      },
      {
        "iso": "AL",
        "name": "Albania",
        "__typename": "country"
      },
      {
        "iso": "DZ",
        "name": "Algeria",
        "__typename": "country"
      },
      {
        "iso": "AS",
        "name": "American Samoa",
        "__typename": "country"
      },
      {
        "iso": "AD",
        "name": "Andorra",
        "__typename": "country"
      },
      {
        "iso": "AO",
        "name": "Angola",
        "__typename": "country"
      },
      {
        "iso": "AI",
        "name": "Anguilla",
        "__typename": "country"
      },
      {
        "iso": "AQ",
        "name": "Antarctica",
        "__typename": "country"
      },
      {
        "iso": "AG",
        "name": "Antigua and Barbuda",
        "__typename": "country"
      },
      {
        "iso": "AR",
        "name": "Argentina",
        "__typename": "country"
      },
      {
        "iso": "AM",
        "name": "Armenia",
        "__typename": "country"
      },
      {
        "iso": "AW",
        "name": "Aruba",
        "__typename": "country"
      },
      {
        "iso": "AU",
        "name": "Australia",
        "__typename": "country"
      },
      {
        "iso": "AT",
        "name": "Austria",
        "__typename": "country"
      },
      {
        "iso": "AZ",
        "name": "Azerbaijan",
        "__typename": "country"
      },
      {
        "iso": "BS",
        "name": "Bahamas",
        "__typename": "country"
      },
      {
        "iso": "BH",
        "name": "Bahrain",
        "__typename": "country"
      },
      {
        "iso": "BD",
        "name": "Bangladesh",
        "__typename": "country"
      },
      {
        "iso": "BB",
        "name": "Barbados",
        "__typename": "country"
      },
      {
        "iso": "BY",
        "name": "Belarus",
        "__typename": "country"
      },
      {
        "iso": "BE",
        "name": "Belgium",
        "__typename": "country"
      },
      {
        "iso": "BZ",
        "name": "Belize",
        "__typename": "country"
      },
      {
        "iso": "BJ",
        "name": "Benin",
        "__typename": "country"
      },
      {
        "iso": "BM",
        "name": "Bermuda",
        "__typename": "country"
      },
      {
        "iso": "BT",
        "name": "Bhutan",
        "__typename": "country"
      },
      {
        "iso": "BO",
        "name": "Bolivia",
        "__typename": "country"
      },
      {
        "iso": "BQ",
        "name": "Bonaire, Saint Eustatius and Saba ",
        "__typename": "country"
      },
      {
        "iso": "BA",
        "name": "Bosnia and Herzegovina",
        "__typename": "country"
      },
      {
        "iso": "BW",
        "name": "Botswana",
        "__typename": "country"
      },
      {
        "iso": "BV",
        "name": "Bouvet Island",
        "__typename": "country"
      },
      {
        "iso": "BR",
        "name": "Brazil",
        "__typename": "country"
      },
      {
        "iso": "IO",
        "name": "British Indian Ocean Territory",
        "__typename": "country"
      },
      {
        "iso": "VG",
        "name": "British Virgin Islands",
        "__typename": "country"
      },
      {
        "iso": "BN",
        "name": "Brunei",
        "__typename": "country"
      },
      {
        "iso": "BG",
        "name": "Bulgaria",
        "__typename": "country"
      },
      {
        "iso": "BF",
        "name": "Burkina Faso",
        "__typename": "country"
      },
      {
        "iso": "BI",
        "name": "Burundi",
        "__typename": "country"
      },
      {
        "iso": "KH",
        "name": "Cambodia",
        "__typename": "country"
      },
      {
        "iso": "CM",
        "name": "Cameroon",
        "__typename": "country"
      },
      {
        "iso": "CA",
        "name": "Canada",
        "__typename": "country"
      },
      {
        "iso": "CV",
        "name": "Cape Verde",
        "__typename": "country"
      },
      {
        "iso": "KY",
        "name": "Cayman Islands",
        "__typename": "country"
      },
      {
        "iso": "CF",
        "name": "Central African Republic",
        "__typename": "country"
      },
      {
        "iso": "TD",
        "name": "Chad",
        "__typename": "country"
      },
      {
        "iso": "CL",
        "name": "Chile",
        "__typename": "country"
      },
      {
        "iso": "CN",
        "name": "China",
        "__typename": "country"
      },
      {
        "iso": "CX",
        "name": "Christmas Island",
        "__typename": "country"
      },
      {
        "iso": "CC",
        "name": "Cocos Islands",
        "__typename": "country"
      },
      {
        "iso": "CO",
        "name": "Colombia",
        "__typename": "country"
      },
      {
        "iso": "KM",
        "name": "Comoros",
        "__typename": "country"
      },
      {
        "iso": "CK",
        "name": "Cook Islands",
        "__typename": "country"
      },
      {
        "iso": "CR",
        "name": "Costa Rica",
        "__typename": "country"
      },
      {
        "iso": "HR",
        "name": "Croatia",
        "__typename": "country"
      },
      {
        "iso": "CU",
        "name": "Cuba",
        "__typename": "country"
      },
      {
        "iso": "CW",
        "name": "Curacao",
        "__typename": "country"
      },
      {
        "iso": "CY",
        "name": "Cyprus",
        "__typename": "country"
      },
      {
        "iso": "CZ",
        "name": "Czechia",
        "__typename": "country"
      },
      {
        "iso": "CD",
        "name": "Democratic Republic of the Congo",
        "__typename": "country"
      },
      {
        "iso": "DK",
        "name": "Denmark",
        "__typename": "country"
      },
      {
        "iso": "DJ",
        "name": "Djibouti",
        "__typename": "country"
      },
      {
        "iso": "DM",
        "name": "Dominica",
        "__typename": "country"
      },
      {
        "iso": "DO",
        "name": "Dominican Republic",
        "__typename": "country"
      },
      {
        "iso": "EC",
        "name": "Ecuador",
        "__typename": "country"
      },
      {
        "iso": "EG",
        "name": "Egypt",
        "__typename": "country"
      },
      {
        "iso": "SV",
        "name": "El Salvador",
        "__typename": "country"
      },
      {
        "iso": "GQ",
        "name": "Equatorial Guinea",
        "__typename": "country"
      },
      {
        "iso": "ER",
        "name": "Eritrea",
        "__typename": "country"
      },
      {
        "iso": "EE",
        "name": "Estonia",
        "__typename": "country"
      },
      {
        "iso": "ET",
        "name": "Ethiopia",
        "__typename": "country"
      },
      {
        "iso": "FK",
        "name": "Falkland Islands",
        "__typename": "country"
      },
      {
        "iso": "FO",
        "name": "Faroe Islands",
        "__typename": "country"
      },
      {
        "iso": "FJ",
        "name": "Fiji",
        "__typename": "country"
      },
      {
        "iso": "FI",
        "name": "Finland",
        "__typename": "country"
      },
      {
        "iso": "FR",
        "name": "France",
        "__typename": "country"
      },
      {
        "iso": "GF",
        "name": "French Guiana",
        "__typename": "country"
      },
      {
        "iso": "PF",
        "name": "French Polynesia",
        "__typename": "country"
      },
      {
        "iso": "TF",
        "name": "French Southern Territories",
        "__typename": "country"
      },
      {
        "iso": "GA",
        "name": "Gabon",
        "__typename": "country"
      },
      {
        "iso": "GM",
        "name": "Gambia",
        "__typename": "country"
      },
      {
        "iso": "GE",
        "name": "Georgia",
        "__typename": "country"
      },
      {
        "iso": "DE",
        "name": "Germany",
        "__typename": "country"
      },
      {
        "iso": "GH",
        "name": "Ghana",
        "__typename": "country"
      },
      {
        "iso": "GI",
        "name": "Gibraltar",
        "__typename": "country"
      },
      {
        "iso": "GR",
        "name": "Greece",
        "__typename": "country"
      },
      {
        "iso": "GL",
        "name": "Greenland",
        "__typename": "country"
      },
      {
        "iso": "GD",
        "name": "Grenada",
        "__typename": "country"
      },
      {
        "iso": "GP",
        "name": "Guadeloupe",
        "__typename": "country"
      },
      {
        "iso": "GU",
        "name": "Guam",
        "__typename": "country"
      },
      {
        "iso": "GT",
        "name": "Guatemala",
        "__typename": "country"
      },
      {
        "iso": "GG",
        "name": "Guernsey",
        "__typename": "country"
      },
      {
        "iso": "GN",
        "name": "Guinea",
        "__typename": "country"
      },
      {
        "iso": "GW",
        "name": "Guinea-Bissau",
        "__typename": "country"
      },
      {
        "iso": "GY",
        "name": "Guyana",
        "__typename": "country"
      },
      {
        "iso": "HT",
        "name": "Haiti",
        "__typename": "country"
      },
      {
        "iso": "HM",
        "name": "Heard Island and McDonald Islands",
        "__typename": "country"
      },
      {
        "iso": "HN",
        "name": "Honduras",
        "__typename": "country"
      },
      {
        "iso": "HK",
        "name": "Hong Kong",
        "__typename": "country"
      },
      {
        "iso": "HU",
        "name": "Hungary",
        "__typename": "country"
      },
      {
        "iso": "IS",
        "name": "Iceland",
        "__typename": "country"
      },
      {
        "iso": "IN",
        "name": "India",
        "__typename": "country"
      },
      {
        "iso": "ID",
        "name": "Indonesia",
        "__typename": "country"
      },
      {
        "iso": "IR",
        "name": "Iran",
        "__typename": "country"
      },
      {
        "iso": "IQ",
        "name": "Iraq",
        "__typename": "country"
      },
      {
        "iso": "IE",
        "name": "Ireland",
        "__typename": "country"
      },
      {
        "iso": "IM",
        "name": "Isle of Man",
        "__typename": "country"
      },
      {
        "iso": "IL",
        "name": "Israel",
        "__typename": "country"
      },
      {
        "iso": "IT",
        "name": "Italy",
        "__typename": "country"
      },
      {
        "iso": "CI",
        "name": "Ivory Coast",
        "__typename": "country"
      },
      {
        "iso": "JM",
        "name": "Jamaica",
        "__typename": "country"
      },
      {
        "iso": "JP",
        "name": "Japan",
        "__typename": "country"
      },
      {
        "iso": "JE",
        "name": "Jersey",
        "__typename": "country"
      },
      {
        "iso": "JO",
        "name": "Jordan",
        "__typename": "country"
      },
      {
        "iso": "KZ",
        "name": "Kazakhstan",
        "__typename": "country"
      },
      {
        "iso": "KE",
        "name": "Kenya",
        "__typename": "country"
      },
      {
        "iso": "KI",
        "name": "Kiribati",
        "__typename": "country"
      },
      {
        "iso": "XK",
        "name": "Kosovo",
        "__typename": "country"
      },
      {
        "iso": "KW",
        "name": "Kuwait",
        "__typename": "country"
      },
      {
        "iso": "KG",
        "name": "Kyrgyzstan",
        "__typename": "country"
      },
      {
        "iso": "LA",
        "name": "Laos",
        "__typename": "country"
      },
      {
        "iso": "LV",
        "name": "Latvia",
        "__typename": "country"
      },
      {
        "iso": "LB",
        "name": "Lebanon",
        "__typename": "country"
      },
      {
        "iso": "LS",
        "name": "Lesotho",
        "__typename": "country"
      },
      {
        "iso": "LR",
        "name": "Liberia",
        "__typename": "country"
      },
      {
        "iso": "LY",
        "name": "Libya",
        "__typename": "country"
      },
      {
        "iso": "LI",
        "name": "Liechtenstein",
        "__typename": "country"
      },
      {
        "iso": "LT",
        "name": "Lithuania",
        "__typename": "country"
      },
      {
        "iso": "LU",
        "name": "Luxembourg",
        "__typename": "country"
      },
      {
        "iso": "MO",
        "name": "Macao",
        "__typename": "country"
      },
      {
        "iso": "MK",
        "name": "Macedonia",
        "__typename": "country"
      },
      {
        "iso": "MG",
        "name": "Madagascar",
        "__typename": "country"
      },
      {
        "iso": "MW",
        "name": "Malawi",
        "__typename": "country"
      },
      {
        "iso": "MY",
        "name": "Malaysia",
        "__typename": "country"
      },
      {
        "iso": "MV",
        "name": "Maldives",
        "__typename": "country"
      },
      {
        "iso": "ML",
        "name": "Mali",
        "__typename": "country"
      },
      {
        "iso": "MT",
        "name": "Malta",
        "__typename": "country"
      },
      {
        "iso": "MH",
        "name": "Marshall Islands",
        "__typename": "country"
      },
      {
        "iso": "MQ",
        "name": "Martinique",
        "__typename": "country"
      },
      {
        "iso": "MR",
        "name": "Mauritania",
        "__typename": "country"
      },
      {
        "iso": "MU",
        "name": "Mauritius",
        "__typename": "country"
      },
      {
        "iso": "YT",
        "name": "Mayotte",
        "__typename": "country"
      },
      {
        "iso": "MX",
        "name": "Mexico",
        "__typename": "country"
      },
      {
        "iso": "FM",
        "name": "Micronesia",
        "__typename": "country"
      },
      {
        "iso": "MD",
        "name": "Moldova",
        "__typename": "country"
      },
      {
        "iso": "MC",
        "name": "Monaco",
        "__typename": "country"
      },
      {
        "iso": "MN",
        "name": "Mongolia",
        "__typename": "country"
      },
      {
        "iso": "ME",
        "name": "Montenegro",
        "__typename": "country"
      },
      {
        "iso": "MS",
        "name": "Montserrat",
        "__typename": "country"
      },
      {
        "iso": "MA",
        "name": "Morocco",
        "__typename": "country"
      },
      {
        "iso": "MZ",
        "name": "Mozambique",
        "__typename": "country"
      },
      {
        "iso": "MM",
        "name": "Myanmar",
        "__typename": "country"
      },
      {
        "iso": "NA",
        "name": "Namibia",
        "__typename": "country"
      },
      {
        "iso": "NR",
        "name": "Nauru",
        "__typename": "country"
      },
      {
        "iso": "NP",
        "name": "Nepal",
        "__typename": "country"
      },
      {
        "iso": "NL",
        "name": "Netherlands",
        "__typename": "country"
      },
      {
        "iso": "AN",
        "name": "Netherlands Antilles",
        "__typename": "country"
      },
      {
        "iso": "NC",
        "name": "New Caledonia",
        "__typename": "country"
      },
      {
        "iso": "NZ",
        "name": "New Zealand",
        "__typename": "country"
      },
      {
        "iso": "NI",
        "name": "Nicaragua",
        "__typename": "country"
      },
      {
        "iso": "NE",
        "name": "Niger",
        "__typename": "country"
      },
      {
        "iso": "NG",
        "name": "Nigeria",
        "__typename": "country"
      },
      {
        "iso": "NU",
        "name": "Niue",
        "__typename": "country"
      },
      {
        "iso": "NF",
        "name": "Norfolk Island",
        "__typename": "country"
      },
      {
        "iso": "MP",
        "name": "Northern Mariana Islands",
        "__typename": "country"
      },
      {
        "iso": "KP",
        "name": "North Korea",
        "__typename": "country"
      },
      {
        "iso": "NO",
        "name": "Norway",
        "__typename": "country"
      },
      {
        "iso": "OM",
        "name": "Oman",
        "__typename": "country"
      },
      {
        "iso": "PK",
        "name": "Pakistan",
        "__typename": "country"
      },
      {
        "iso": "PW",
        "name": "Palau",
        "__typename": "country"
      },
      {
        "iso": "PS",
        "name": "Palestinian Territory",
        "__typename": "country"
      },
      {
        "iso": "PA",
        "name": "Panama",
        "__typename": "country"
      },
      {
        "iso": "PG",
        "name": "Papua New Guinea",
        "__typename": "country"
      },
      {
        "iso": "PY",
        "name": "Paraguay",
        "__typename": "country"
      },
      {
        "iso": "PE",
        "name": "Peru",
        "__typename": "country"
      },
      {
        "iso": "PH",
        "name": "Philippines",
        "__typename": "country"
      },
      {
        "iso": "PN",
        "name": "Pitcairn",
        "__typename": "country"
      },
      {
        "iso": "PL",
        "name": "Poland",
        "__typename": "country"
      },
      {
        "iso": "PT",
        "name": "Portugal",
        "__typename": "country"
      },
      {
        "iso": "PR",
        "name": "Puerto Rico",
        "__typename": "country"
      },
      {
        "iso": "QA",
        "name": "Qatar",
        "__typename": "country"
      },
      {
        "iso": "CG",
        "name": "Republic of the Congo",
        "__typename": "country"
      },
      {
        "iso": "RE",
        "name": "Reunion",
        "__typename": "country"
      },
      {
        "iso": "RO",
        "name": "Romania",
        "__typename": "country"
      },
      {
        "iso": "RU",
        "name": "Russia",
        "__typename": "country"
      },
      {
        "iso": "RW",
        "name": "Rwanda",
        "__typename": "country"
      },
      {
        "iso": "BL",
        "name": "Saint Barthelemy",
        "__typename": "country"
      },
      {
        "iso": "SH",
        "name": "Saint Helena",
        "__typename": "country"
      },
      {
        "iso": "KN",
        "name": "Saint Kitts and Nevis",
        "__typename": "country"
      },
      {
        "iso": "LC",
        "name": "Saint Lucia",
        "__typename": "country"
      },
      {
        "iso": "MF",
        "name": "Saint Martin",
        "__typename": "country"
      },
      {
        "iso": "PM",
        "name": "Saint Pierre and Miquelon",
        "__typename": "country"
      },
      {
        "iso": "VC",
        "name": "Saint Vincent and the Grenadines",
        "__typename": "country"
      },
      {
        "iso": "WS",
        "name": "Samoa",
        "__typename": "country"
      },
      {
        "iso": "SM",
        "name": "San Marino",
        "__typename": "country"
      },
      {
        "iso": "ST",
        "name": "Sao Tome and Principe",
        "__typename": "country"
      },
      {
        "iso": "SA",
        "name": "Saudi Arabia",
        "__typename": "country"
      },
      {
        "iso": "SN",
        "name": "Senegal",
        "__typename": "country"
      },
      {
        "iso": "RS",
        "name": "Serbia",
        "__typename": "country"
      },
      {
        "iso": "CS",
        "name": "Serbia and Montenegro",
        "__typename": "country"
      },
      {
        "iso": "SC",
        "name": "Seychelles",
        "__typename": "country"
      },
      {
        "iso": "SL",
        "name": "Sierra Leone",
        "__typename": "country"
      },
      {
        "iso": "SG",
        "name": "Singapore",
        "__typename": "country"
      },
      {
        "iso": "SX",
        "name": "Sint Maarten",
        "__typename": "country"
      },
      {
        "iso": "SK",
        "name": "Slovakia",
        "__typename": "country"
      },
      {
        "iso": "SI",
        "name": "Slovenia",
        "__typename": "country"
      },
      {
        "iso": "SB",
        "name": "Solomon Islands",
        "__typename": "country"
      },
      {
        "iso": "SO",
        "name": "Somalia",
        "__typename": "country"
      },
      {
        "iso": "ZA",
        "name": "South Africa",
        "__typename": "country"
      },
      {
        "iso": "GS",
        "name": "South Georgia and the South Sandwich Islands",
        "__typename": "country"
      },
      {
        "iso": "KR",
        "name": "South Korea",
        "__typename": "country"
      },
      {
        "iso": "SS",
        "name": "South Sudan",
        "__typename": "country"
      },
      {
        "iso": "ES",
        "name": "Spain",
        "__typename": "country"
      },
      {
        "iso": "LK",
        "name": "Sri Lanka",
        "__typename": "country"
      },
      {
        "iso": "SD",
        "name": "Sudan",
        "__typename": "country"
      },
      {
        "iso": "SR",
        "name": "Suriname",
        "__typename": "country"
      },
      {
        "iso": "SJ",
        "name": "Svalbard and Jan Mayen",
        "__typename": "country"
      },
      {
        "iso": "SZ",
        "name": "Swaziland",
        "__typename": "country"
      },
      {
        "iso": "SE",
        "name": "Sweden",
        "__typename": "country"
      },
      {
        "iso": "CH",
        "name": "Switzerland",
        "__typename": "country"
      },
      {
        "iso": "SY",
        "name": "Syria",
        "__typename": "country"
      },
      {
        "iso": "TW",
        "name": "Taiwan",
        "__typename": "country"
      },
      {
        "iso": "TJ",
        "name": "Tajikistan",
        "__typename": "country"
      },
      {
        "iso": "TZ",
        "name": "Tanzania",
        "__typename": "country"
      },
      {
        "iso": "TH",
        "name": "Thailand",
        "__typename": "country"
      },
      {
        "iso": "TL",
        "name": "Timor Leste",
        "__typename": "country"
      },
      {
        "iso": "TG",
        "name": "Togo",
        "__typename": "country"
      },
      {
        "iso": "TK",
        "name": "Tokelau",
        "__typename": "country"
      },
      {
        "iso": "TO",
        "name": "Tonga",
        "__typename": "country"
      },
      {
        "iso": "TT",
        "name": "Trinidad and Tobago",
        "__typename": "country"
      },
      {
        "iso": "TN",
        "name": "Tunisia",
        "__typename": "country"
      },
      {
        "iso": "TR",
        "name": "Turkey",
        "__typename": "country"
      },
      {
        "iso": "TM",
        "name": "Turkmenistan",
        "__typename": "country"
      },
      {
        "iso": "TC",
        "name": "Turks and Caicos Islands",
        "__typename": "country"
      },
      {
        "iso": "TV",
        "name": "Tuvalu",
        "__typename": "country"
      },
      {
        "iso": "UG",
        "name": "Uganda",
        "__typename": "country"
      },
      {
        "iso": "UA",
        "name": "Ukraine",
        "__typename": "country"
      },
      {
        "iso": "AE",
        "name": "United Arab Emirates",
        "__typename": "country"
      },
      {
        "iso": "GB",
        "name": "United Kingdom",
        "__typename": "country"
      },
      {
        "iso": "US",
        "name": "United States",
        "__typename": "country"
      },
      {
        "iso": "UM",
        "name": "United States Minor Outlying Islands",
        "__typename": "country"
      },
      {
        "iso": "UY",
        "name": "Uruguay",
        "__typename": "country"
      },
      {
        "iso": "VI",
        "name": "U.S. Virgin Islands",
        "__typename": "country"
      },
      {
        "iso": "UZ",
        "name": "Uzbekistan",
        "__typename": "country"
      },
      {
        "iso": "VU",
        "name": "Vanuatu",
        "__typename": "country"
      },
      {
        "iso": "VA",
        "name": "Vatican",
        "__typename": "country"
      },
      {
        "iso": "VE",
        "name": "Venezuela",
        "__typename": "country"
      },
      {
        "iso": "VN",
        "name": "Vietnam",
        "__typename": "country"
      },
      {
        "iso": "WF",
        "name": "Wallis and Futuna",
        "__typename": "country"
      },
      {
        "iso": "EH",
        "name": "Western Sahara",
        "__typename": "country"
      },
      {
        "iso": "YE",
        "name": "Yemen",
        "__typename": "country"
      },
      {
        "iso": "ZM",
        "name": "Zambia",
        "__typename": "country"
      },
      {
        "iso": "ZW",
        "name": "Zimbabwe",
        "__typename": "country"
      }
    ]
  }
}
